{"ppb_form_data_order":["1499937733582"],"1499937733582_data":["{\"id\":\"1499937733582\",\"shortcode\":\"ppb_speaker_grid\",\"ppb_speaker_grid_title\":\"Title\",\"ppb_speaker_grid_slug\":\"\",\"ppb_speaker_grid_columns\":\"5\",\"ppb_speaker_grid_speakercat\":\"\",\"ppb_speaker_grid_items\":\"10\",\"ppb_speaker_grid_effect\":\"0\",\"ppb_speaker_grid_margin_top\":\"\",\"ppb_speaker_grid_margin_bottom\":\"\",\"ppb_speaker_grid_margin_left\":\"\",\"ppb_speaker_grid_margin_right\":\"\",\"ppb_speaker_grid_custom_css\":\"\"}"],"1499937733582_size":["one"]}